LICENSE
alist/.DS_Store
alist/__init__.py
alist/__main__.py
alist/cmd/.DS_Store
alist/cmd/__init__.py
alist/cmd/download.py
alist/cmd/fuse/.DS_Store
alist/cmd/fuse/__init__.py
alist/cmd/fuse/__main__.py
alist/cmd/fuse/util/.DS_Store
alist/cmd/fuse/util/__fuse_monkey_patch.py
alist/cmd/fuse/util/__init__.py
alist/cmd/fuse/util/fuser.py
alist/cmd/fuse/util/log.py
alist/cmd/fuse/util/predicate.py
alist/cmd/fuse/util/strm.py
alist/cmd/init.py
alist/cmd/iterdir.py
alist/cmd/rename.py
alist/cmd/update_115_cookies.py
alist/cmd/upload.py
alist/component/.DS_Store
alist/component/__init__.py
alist/component/admin/.DS_Store
alist/component/admin/__init__.py
alist/component/admin/driver.py
alist/component/admin/index.py
alist/component/admin/meta.py
alist/component/admin/setting.py
alist/component/admin/storage.py
alist/component/admin/task.py
alist/component/admin/user.py
alist/component/client.py
alist/component/fs.py
alist/py.typed
alist/tool/.DS_Store
alist/tool/__init__.py
python_alist-0.0.14.dist-info/LICENSE
python_alist-0.0.14.dist-info/METADATA
python_alist-0.0.14.dist-info/WHEEL
python_alist-0.0.14.dist-info/entry_points.txt
python_alist-0.0.14.dist-info/RECORD
