Metadata-Version: 2.1
Name: python-alist
Version: 0.0.14
Summary: Python wrapper for alist.
Home-page: https://github.com/ChenyangGao/python-alist
License: MIT
Keywords: alist,client
Author: ChenyangGao
Author-email: wosiwujm@gmail.com
Requires-Python: >=3.12,<4.0
Classifier: Development Status :: 4 - Beta
Classifier: Intended Audience :: Developers
Classifier: License :: OSI Approved :: MIT License
Classifier: Operating System :: OS Independent
Classifier: Programming Language :: Python
Classifier: Programming Language :: Python :: 3
Classifier: Programming Language :: Python :: 3.12
Classifier: Programming Language :: Python :: 3.13
Classifier: Programming Language :: Python :: 3 :: Only
Classifier: Topic :: Software Development
Classifier: Topic :: Software Development :: Libraries
Classifier: Topic :: Software Development :: Libraries :: Python Modules
Requires-Dist: ed2k (>=0.0.2.1)
Requires-Dist: glob_pattern
Requires-Dist: http_response
Requires-Dist: httpx
Requires-Dist: httpx_request (>=0.1.4)
Requires-Dist: multidict
Requires-Dist: orjson
Requires-Dist: p115qrcode (>=0.0.4)
Requires-Dist: path_ignore_pattern
Requires-Dist: python-argtools (>=0.0.2)
Requires-Dist: python-asynctools (>=0.1.3.4)
Requires-Dist: python-dateutil
Requires-Dist: python-dictattr (>=0.0.4)
Requires-Dist: python-download (>=0.0.3)
Requires-Dist: python-filewrap (>=0.2.8)
Requires-Dist: python-http_request (>=0.0.7)
Requires-Dist: python-httpfile (>=0.0.5)
Requires-Dist: python-iterutils (>=0.2.5.5)
Requires-Dist: python-property (>=0.0.3)
Requires-Dist: python-retrytools (>=0.0.2)
Requires-Dist: python-undefined (>=0.0.3)
Requires-Dist: yarl
Project-URL: Repository, https://github.com/ChenyangGao/python-alist
